Metadata-Version: 2.4
Name: shap-0.47.3.dev8-offline-fork-for-myevae
Version: 0.0.1
Summary: An offline fork of https://pypi.org/project/shap/, which exists to allow SHAP to be run on MyeVAE (https://pypi.org/project/myevae/)
Author-email: Chang Jia Geng <changjiageng@u.nus.edu>
License: MIT License
Classifier: License :: OSI Approved :: MIT License
Requires-Python: >=3.9
License-File: LICENSE
Requires-Dist: numpy
Requires-Dist: scipy
Requires-Dist: scikit-learn
Requires-Dist: pandas
Requires-Dist: tqdm>=4.27.0
Requires-Dist: packaging>20.9
Requires-Dist: slicer==0.0.8
Requires-Dist: numba>=0.54
Requires-Dist: cloudpickle
Requires-Dist: typing-extensions
Provides-Extra: plots
Requires-Dist: matplotlib; extra == "plots"
Requires-Dist: ipython; extra == "plots"
Provides-Extra: others
Requires-Dist: lime; extra == "others"
Provides-Extra: docs
Requires-Dist: matplotlib; extra == "docs"
Requires-Dist: ipython; extra == "docs"
Requires-Dist: numpydoc; extra == "docs"
Requires-Dist: sphinx_rtd_theme; extra == "docs"
Requires-Dist: sphinx; extra == "docs"
Requires-Dist: nbsphinx; extra == "docs"
Requires-Dist: sphinx_github_changelog; extra == "docs"
Requires-Dist: myst-parser; extra == "docs"
Requires-Dist: requests; extra == "docs"
Requires-Dist: ipywidgets; extra == "docs"
Provides-Extra: test-core
Requires-Dist: pytest; extra == "test-core"
Requires-Dist: pytest-mpl; extra == "test-core"
Requires-Dist: pytest-cov; extra == "test-core"
Requires-Dist: mypy; extra == "test-core"
Provides-Extra: test
Requires-Dist: pytest; extra == "test"
Requires-Dist: pytest-mpl; extra == "test"
Requires-Dist: pytest-cov; extra == "test"
Requires-Dist: xgboost; extra == "test"
Requires-Dist: lightgbm; extra == "test"
Requires-Dist: catboost; extra == "test"
Requires-Dist: gpboost; extra == "test"
Requires-Dist: ngboost; extra == "test"
Requires-Dist: pyspark; extra == "test"
Requires-Dist: pyod; extra == "test"
Requires-Dist: transformers<=4.49.0; sys_platform == "darwin" and extra == "test"
Requires-Dist: transformers; sys_platform != "darwin" and extra == "test"
Requires-Dist: tf-keras; extra == "test"
Requires-Dist: protobuf==3.20.3; extra == "test"
Requires-Dist: torch==2.2.0; sys_platform == "darwin" and extra == "test"
Requires-Dist: torch; sys_platform != "darwin" and extra == "test"
Requires-Dist: torchvision; extra == "test"
Requires-Dist: tensorflow; extra == "test"
Requires-Dist: sentencepiece; extra == "test"
Requires-Dist: opencv-python; extra == "test"
Requires-Dist: numpy<2.0; extra == "test"
Requires-Dist: causalml; extra == "test"
Requires-Dist: selenium; extra == "test"
Provides-Extra: test-notebooks
Requires-Dist: jupyter; extra == "test-notebooks"
Requires-Dist: nbconvert; extra == "test-notebooks"
Requires-Dist: nbformat; extra == "test-notebooks"
Requires-Dist: nlp; extra == "test-notebooks"
Requires-Dist: transformers; extra == "test-notebooks"
Requires-Dist: datasets; extra == "test-notebooks"
Requires-Dist: keras; extra == "test-notebooks"
Dynamic: license-file
